setup.py
vbrnrt_probability/Binomialdistribution.py
vbrnrt_probability/Gaussiandistribution.py
vbrnrt_probability/Generaldistribution.py
vbrnrt_probability/__init__.py
vbrnrt_probability/setup.py
vbrnrt_probability.egg-info/PKG-INFO
vbrnrt_probability.egg-info/SOURCES.txt
vbrnrt_probability.egg-info/dependency_links.txt
vbrnrt_probability.egg-info/not-zip-safe
vbrnrt_probability.egg-info/top_level.txt