Metadata-Version: 1.0
Name: vbrnrt-probability
Version: 0.1
Summary: Gaussian and Binomial distributions
Home-page: UNKNOWN
Author: Lawrence
Author-email: lawrence.lee@commscope.com
License: UNKNOWN
Platform: UNKNOWN
